MANIFEST.in
README.md
requirements.txt
setup.py
ipagare/__init__.py
ipagare/__init__.pyc
ipagare/error.py
ipagare/error.pyc
ipagare/gateway.py
ipagare/gateway.pyc
ipagare/model.py
ipagare/model.pyc
python_ipagare.egg-info/PKG-INFO
python_ipagare.egg-info/SOURCES.txt
python_ipagare.egg-info/dependency_links.txt
python_ipagare.egg-info/requires.txt
python_ipagare.egg-info/top_level.txt
tests/__init__.py
tests/test_gateway.py