Metadata-Version: 1.0
Name: python-ipagare
Version: 0.0.7
Summary: python api to ipagare webservices
Home-page: http://github.com/quatix/python-ipagare
Author: Marcel Nicolay
Author-email: marcelnicolay@gmail.com
License: UNKNOWN
Platform: UNKNOWN
